LICENSE
MANIFEST.in
README.md
requirements.txt
setup.py
conf/monolithe.ini
nuage_vsd_sim.egg-info/PKG-INFO
nuage_vsd_sim.egg-info/SOURCES.txt
nuage_vsd_sim.egg-info/dependency_links.txt
nuage_vsd_sim.egg-info/entry_points.txt
nuage_vsd_sim.egg-info/requires.txt
nuage_vsd_sim.egg-info/top_level.txt
nuagevsdsim/__init__.py
nuagevsdsim/shell.py
nuagevsdsim/common/__init__.py
nuagevsdsim/common/nusimconfig.py
nuagevsdsim/common/utils.py
nuagevsdsim/simentities/__init__.py
nuagevsdsim/simentities/nusimaddressmap.py
nuagevsdsim/simentities/nusimaddressrange.py
nuagevsdsim/simentities/nusimaggregatemetadata.py
nuagevsdsim/simentities/nusimalarm.py
nuagevsdsim/simentities/nusimallalarm.py
nuagevsdsim/simentities/nusimallgateway.py
nuagevsdsim/simentities/nusimallredundancygroup.py
nuagevsdsim/simentities/nusimapplication.py
nuagevsdsim/simentities/nusimapplicationbinding.py
nuagevsdsim/simentities/nusimapplicationperformancemanagement.py
nuagevsdsim/simentities/nusimapplicationperformancemanagementbinding.py
nuagevsdsim/simentities/nusimautodiscovercluster.py
nuagevsdsim/simentities/nusimautodiscovereddatacenter.py
nuagevsdsim/simentities/nusimautodiscoveredgateway.py
nuagevsdsim/simentities/nusimautodiscoverhypervisorfromcluster.py
nuagevsdsim/simentities/nusimavatar.py
nuagevsdsim/simentities/nusimbfdsession.py
nuagevsdsim/simentities/nusimbgpneighbor.py
nuagevsdsim/simentities/nusimbgppeer.py
nuagevsdsim/simentities/nusimbgpprofile.py
nuagevsdsim/simentities/nusimbootstrap.py
nuagevsdsim/simentities/nusimbootstrapactivation.py
nuagevsdsim/simentities/nusimbrconnection.py
nuagevsdsim/simentities/nusimbridgeinterface.py
nuagevsdsim/simentities/nusimbulkstatistics.py
nuagevsdsim/simentities/nusimcaptiveportalprofile.py
nuagevsdsim/simentities/nusimcertificate.py
nuagevsdsim/simentities/nusimcloudmgmtsystem.py
nuagevsdsim/simentities/nusimcommand.py
nuagevsdsim/simentities/nusimconnectionendpoint.py
nuagevsdsim/simentities/nusimcontainer.py
nuagevsdsim/simentities/nusimcontainerinterface.py
nuagevsdsim/simentities/nusimcontainerresync.py
nuagevsdsim/simentities/nusimcosremarkingpolicy.py
nuagevsdsim/simentities/nusimcosremarkingpolicytable.py
nuagevsdsim/simentities/nusimcsnatpool.py
