Metadata-Version: 1.2
Name: nuage-vsd-sim
Version: 5.3.3
Summary: API simulator of Nuage VSD
Home-page: http://nuagenetworks.net/
Author: nuage networks
Author-email: opensource@nuagenetworks.net
License: UNKNOWN
Keywords: API simulator of Nuage VSD
Platform: UNKNOWN
Classifier: Development Status :: 4 - Beta
Classifier: Environment :: Console
Classifier: Intended Audience :: Information Technology
Classifier: Intended Audience :: System Administrators
Classifier: License :: OSI Approved :: BSD License
Classifier: Natural Language :: English
Classifier: Operating System :: MacOS
Classifier: Operating System :: POSIX :: Linux
Classifier: Programming Language :: Python :: 2
Classifier: Programming Language :: Python :: 2.7
Classifier: Topic :: System :: Networking
Classifier: Topic :: System :: Systems Administration
Classifier: Topic :: Utilities
Requires-Python: >=2.6, <3
